{
    "categories": [{
        "categoryName": "Wall paintings",
        "categoryImagePath": "content/images/categoryimages/image1",
        "categoryId": 1,
        "subcategoryList": [{
            "categoryName": "Wall Drifts",
            "categoryImagePath": "content/images/categoryimages/image2",
            "categoryId": 12,
            "categoryStatus": "Active",
            "subcategoryList": null
        }, {
            "categoryName": "Wall Hangings",
            "categoryImagePath": "",
            "categoryId": 13,
            "categoryStatus": "Active",
            "subcategoryList": null
        }]
    },
    {
        "categoryName": "Wall paintings1",
        "categoryImagePath": "content/images/categoryimages/image1",
        "categoryId": 2,
        "subcategoryList": [{
            "categoryName": "Wall Drifts",
            "categoryImagePath": "content/images/categoryimages/image2",
            "categoryId": 22,
            "categoryStatus": "Active",
            "subcategoryList": null
        }, {
            "categoryName": "Wall Hangings",
            "categoryImagePath": "",
            "categoryId": 23,
            "categoryStatus": "Active",
            "subcategoryList": null
        },
        {
            "categoryName": "Wall Hangings",
            "categoryImagePath": "",
            "categoryId": 24,
            "categoryStatus": "InActive",
            "subcategoryList": null
        },
        {
            "categoryName": "Wall Hangings",
            "categoryImagePath": "",
            "categoryId": 25,
            "categoryStatus": "InActive",
            "subcategoryList": null
        }]
    },
    {
        "categoryName": "Wall paintings3",
        "categoryImagePath": "content/images/categoryimages/image1",
        "categoryId": 3,
        "subcategoryList": []
    }]

}